inzicht/__init__.py
inzicht/aio/__init__.py
inzicht/aio/crud/__init__.py
inzicht/aio/crud/factories.py
inzicht/aio/crud/generic.py
inzicht/aio/crud/interfaces.py
inzicht/crud/__init__.py
inzicht/crud/errors.py
inzicht/crud/factories.py
inzicht/crud/generic.py
inzicht/crud/interfaces.py
inzicht/declarative.py
inzicht/py.typed
inzicht-0.1.22.dist-info/METADATA
inzicht-0.1.22.dist-info/WHEEL
inzicht-0.1.22.dist-info/RECORD
