Metadata-Version: 2.3
Name: inzicht
Version: 0.1.22
Summary: A Python library that provides generic CRUD functionality streamlining database operations.
Author: Alexey Naumov
Author-email: digitaal.vier@gmail.com
Requires-Python: >=3.10
Classifier: Programming Language :: Python :: 3
Classifier: Programming Language :: Python :: 3.10
Classifier: Programming Language :: Python :: 3.11
Classifier: Programming Language :: Python :: 3.12
Classifier: Programming Language :: Python :: 3.13
Requires-Dist: aiosqlite (>=0.21.0,<0.22.0)
Requires-Dist: sqlalchemy[asyncio] (>=2.0.38,<3.0.0)
